mbrowse/__init__.py
mbrowse/admin.py
mbrowse/apps.py
mbrowse/filter.py
mbrowse/manage.py
mbrowse/sitetrees.py
mbrowse/tables.py
mbrowse/tasks.py
mbrowse/test_settings.py
mbrowse/urls.py
mbrowse/forms/__init__.py
mbrowse/forms/forms_annotations.py
mbrowse/forms/forms_general.py
mbrowse/forms/forms_libraries.py
mbrowse/forms/forms_search.py
mbrowse/migrations/0001_initial.py
mbrowse/migrations/0002_CUSTOM_IMPORT_DATA.py
mbrowse/migrations/__init__.py
mbrowse/migrations/backup/0002_CUSTOM_IMPORT_DATA.py
mbrowse/migrations/backup/__init__.py
mbrowse/models/__init__.py
mbrowse/models/models_annotations.py
mbrowse/models/models_compounds.py
mbrowse/models/models_cpeaks.py
mbrowse/models/models_dpeaks.py
mbrowse/models/models_general.py
mbrowse/models/models_libraries.py
mbrowse/models/models_search.py
mbrowse/models/models_speaks.py
mbrowse/templates/base.html
mbrowse/templates/template_structure.txt
mbrowse/templates/gfiles/index.html
mbrowse/templates/mbrowse/cannotation_download_result.html
mbrowse/templates/mbrowse/canns_download.html
mbrowse/templates/mbrowse/cpeakgroup_annotations.html
mbrowse/templates/mbrowse/cpeakgroup_annotations_all.html
mbrowse/templates/mbrowse/cpeakgroup_spectral_matching_summary.html
mbrowse/templates/mbrowse/cpeakgroup_summary.html
mbrowse/templates/mbrowse/cpeakgroup_summary_all.html
mbrowse/templates/mbrowse/cpeakmeta_summary.html
mbrowse/templates/mbrowse/eics.html
mbrowse/templates/mbrowse/form_field_row.html
mbrowse/templates/mbrowse/frag4feature.html
mbrowse/templates/mbrowse/general_summary.html
mbrowse/templates/mbrowse/libraryspectrasource_form.html
mbrowse/templates/mbrowse/metabinputdata_form.html
mbrowse/templates/mbrowse/mfile_form.html
mbrowse/templates/mbrowse/mfile_summary.html
mbrowse/templates/mbrowse/run_form.html
mbrowse/templates/mbrowse/search_result_summary.html
mbrowse/templates/mbrowse/searchfragparam_form.html
mbrowse/templates/mbrowse/searchmzparam_form.html
mbrowse/templates/mbrowse/searchnmparam_form.html
django_mbrowse-0.0.2.dist-info/LICENSE
django_mbrowse-0.0.2.dist-info/METADATA
django_mbrowse-0.0.2.dist-info/WHEEL
django_mbrowse-0.0.2.dist-info/top_level.txt
django_mbrowse-0.0.2.dist-info/RECORD
